htmlark
