Metadata-Version: 1.1
Name: HTMLArk
Version: 1.0.0
Summary: Pack a webpage including support files into a single HTML file.
Home-page: https://github.com/BitLooter/htmlark
Author: David Powell
Author-email: BitLooter@users.noreply.github.com
License: MIT
Keywords: development html webpage css javascript
Platform: UNKNOWN
Classifier: Development Status :: 5 - Production/Stable
Classifier: Intended Audience :: End Users/Desktop
Classifier: Intended Audience :: Developers
Classifier: License :: OSI Approved :: MIT License
Classifier: Operating System :: OS Independent
Classifier: Programming Language :: Python
Classifier: Programming Language :: Python :: 3
Classifier: Programming Language :: Python :: 3.5
Classifier: Topic :: Software Development :: Libraries
Classifier: Topic :: Software Development :: Libraries :: Python Modules
Classifier: Topic :: System :: Archiving
Classifier: Topic :: Text Processing :: Markup :: HTML
